ckanext/__init__.py
ckanext/ldap/__init__.py
ckanext/ldap/cli.py
ckanext/ldap/plugin.py
ckanext/ldap/lib/__init__.py
ckanext/ldap/lib/exceptions.py
ckanext/ldap/lib/helpers.py
ckanext/ldap/lib/search.py
ckanext/ldap/logic/__init__.py
ckanext/ldap/logic/auth.py
ckanext/ldap/migration/ldap/README
ckanext/ldap/migration/ldap/alembic.ini
ckanext/ldap/migration/ldap/env.py
ckanext/ldap/migration/ldap/script.py.mako
ckanext/ldap/migration/ldap/versions/a9d372ce374d_initialisation.py
ckanext/ldap/model/__init__.py
ckanext/ldap/model/ldap_user.py
ckanext/ldap/routes/__init__.py
ckanext/ldap/routes/_helpers.py
ckanext/ldap/routes/login.py
ckanext/ldap/theme/templates/user/login.html
ckanext_ldap-4.1.2.dist-info/licenses/LICENSE
docs/_scripts/gen_api_pages.py
tests/routes/__init__.py
tests/routes/test_helpers.py
ckanext_ldap-4.1.2.dist-info/METADATA
ckanext_ldap-4.1.2.dist-info/WHEEL
ckanext_ldap-4.1.2.dist-info/entry_points.txt
ckanext_ldap-4.1.2.dist-info/top_level.txt
ckanext_ldap-4.1.2.dist-info/RECORD
